gaston/__init__.py
gaston/menu.py
gaston/templates/gaston/menu.html
gaston/templatetags/__init__.py
gaston/templatetags/gaston_tags.py
django_gaston-0.4.1.dist-info/LICENSE
django_gaston-0.4.1.dist-info/METADATA
django_gaston-0.4.1.dist-info/WHEEL
django_gaston-0.4.1.dist-info/top_level.txt
django_gaston-0.4.1.dist-info/RECORD
