Metadata-Version: 2.1
Name: django-gaston
Version: 0.4.1
Summary: A django menu generator
Home-page: https://github.com/Hyde-Tek/django-gaston/
Author: Hyde Tek
Requires-Python: >=3.6
License-File: LICENSE
